ccl_bplist.py
nska_deserialize.py
nska_deserialize-1.4.0.dist-info/LICENSE
nska_deserialize-1.4.0.dist-info/METADATA
nska_deserialize-1.4.0.dist-info/WHEEL
nska_deserialize-1.4.0.dist-info/top_level.txt
nska_deserialize-1.4.0.dist-info/RECORD
