Metadata-Version: 2.1
Name: nska_deserialize
Version: 1.4.0
Summary: Convert NSKeyedArchiver plist into a deserialized human readable plist
Home-page: https://github.com/ydkhatri/nska_deserialize
Author: Yogesh Khatri
Author-email: yogesh@swiftforensics.com
License: MIT License
Classifier: Programming Language :: Python :: 3
Classifier: License :: OSI Approved :: MIT License
Classifier: Operating System :: OS Independent
Requires-Python: >=3.6
License-File: LICENSE
Requires-Dist: biplist
